_examples/__init__.py
_examples/ex3.py
_examples/example_from_notebook.py
_examples/plot_ex1.py
_examples/subsection/__init__.py
_examples/subsection/ex2.py
_examples/subsection/example_from_notebook_subsection.py
examples/__init__.py
examples/ex3.py
examples/plot_ex1.py
examples/subsection/__init__.py
examples/subsection/ex2.py
py_qs_example/__init__.py
py_qs_example/mymodule.py
py_qs_example/mypackage/__init__.py
py_qs_example/mypackage/module.py
tests/__init__.py
tests/test_mymodule.py
py_qs_example-0.2.11.dist-info/LICENSE.md
py_qs_example-0.2.11.dist-info/METADATA
py_qs_example-0.2.11.dist-info/WHEEL
py_qs_example-0.2.11.dist-info/entry_points.txt
py_qs_example-0.2.11.dist-info/top_level.txt
py_qs_example-0.2.11.dist-info/RECORD
